azure/__init__.py
azure/cli/__init__.py
azure/cli/command_modules/__init__.py
azure/cli/command_modules/botservice/__init__.py
azure/cli/command_modules/botservice/_client_factory.py
azure/cli/command_modules/botservice/_exception_handler.py
azure/cli/command_modules/botservice/_help.py
azure/cli/command_modules/botservice/_params.py
azure/cli/command_modules/botservice/adal_authenticator.py
azure/cli/command_modules/botservice/bot_json_formatter.py
azure/cli/command_modules/botservice/bot_publish_prep.py
azure/cli/command_modules/botservice/bot_template_deployer.py
azure/cli/command_modules/botservice/channel_operations.py
azure/cli/command_modules/botservice/commands.py
azure/cli/command_modules/botservice/constants.py
azure/cli/command_modules/botservice/converged_app.py
azure/cli/command_modules/botservice/custom.py
azure/cli/command_modules/botservice/functionapp.template.json
azure/cli/command_modules/botservice/http_response_validator.py
azure/cli/command_modules/botservice/kudu_client.py
azure/cli/command_modules/botservice/typescript.web.config
azure/cli/command_modules/botservice/web.config
azure/cli/command_modules/botservice/web_app_operations.py
azure/cli/command_modules/botservice/webapp.template.json
azure/cli/command_modules/botservice/webappv4.template.json
opal_azure_cli_botservice-0.2.4.dist-info/METADATA
opal_azure_cli_botservice-0.2.4.dist-info/WHEEL
opal_azure_cli_botservice-0.2.4.dist-info/top_level.txt
opal_azure_cli_botservice-0.2.4.dist-info/RECORD
